pytils/__init__.py
pytils/configurator.py
pytils/handler_telegram.py
pytils/logger.py
pytils/pandas_table.py
pytils/pickler.py
pytils/retry.py
pytils/singleton.py
tests/__init__.py
tests/test_configurator.py
tests/test_logger.py
tests/test_retries.py
tests/test_singleton.py
pytils_functions-0.1.10.dist-info/LICENSE
pytils_functions-0.1.10.dist-info/LICENSE.md
pytils_functions-0.1.10.dist-info/METADATA
pytils_functions-0.1.10.dist-info/WHEEL
pytils_functions-0.1.10.dist-info/top_level.txt
pytils_functions-0.1.10.dist-info/RECORD
