Metadata-Version: 2.1
Name: pytils-functions
Version: 0.1.10
Summary: Utils for data python project
Home-page: https://github.com/Whisperes/pytils
Author: Whispered
Author-email: bluden99@example.com
Classifier: Programming Language :: Python :: 3
Classifier: License :: OSI Approved :: MIT License
Classifier: Operating System :: OS Independent
Requires-Python: >=3.6
License-File: LICENSE
License-File: LICENSE.md
Requires-Dist: requests
Requires-Dist: dill
Requires-Dist: coloredlogs
Requires-Dist: pytest
